{
  "id": "scooter-dragonet",
  "name": "Scooter Dragonet",
  "scientificName": "Synchiropus ocellatus",
  "taxonomy": {
    "waterType": "saltwater",
    "habitat": "reef",
    "region": "indo-pacific",
    "family": "Callionymidae"
  },
  "appearance": {
    "bodyShape": "unusual",
    "sizeCategory": "small",
    "primaryColor": "red",
    "pattern": "spotted"
  },
  "image": "assets/fish/scooter-dragonet.svg",
  "colors": {
    "primary": "#F44336",
    "secondary": "#FF9800",
    "accent": "#000000"
  },
  "facts": [
    {
      "text": "I'm called a scooter because I scoot along the bottom looking for food!",
      "category": "behavior",
      "sourceId": "fishbase"
    },
    {
      "text": "I'm red with orange spots - I'm like a little fire engine scooting around!",
      "category": "biology",
      "sourceId": "fishbase"
    },
    {
      "text": "I'm easier to feed than mandarins because I'll eat frozen food!",
      "category": "behavior",
      "sourceId": "captive-bred"
    }
  ],
  "profile": {
    "habitat": "Sandy and rubble areas of the Indo-Pacific",
    "diet": "Small crustaceans and frozen foods",
    "size": "Up to 3 inches (8 cm)",
    "lifespan": "5-8 years"
  }
}
